mach_info
