Metadata-Version: 1.0
Name: django-snikt
Version: 1.2.4
Summary: Web front end for hardware provisioning.
Home-page: UNKNOWN
Author: Shawn Berger
Author-email: shberger@ebay.com
License: UNKNOWN
Platform: UNKNOWN
Classifier: Environment :: Web Environment
Classifier: Framework :: Django
Classifier: Intended Audience :: Developers
Classifier: Operating System :: OS Independent
Classifier: Programming Language :: Python
Classifier: Programming Language :: Python :: 2.6
Classifier: Topic :: Internet :: WWW/HTTP
Classifier: Topic :: Internet :: WWW/HTTP :: Dynamic Content
